scipy_maxentropy/__init__.py
scipy_maxentropy/info.py
scipy_maxentropy/maxentropy.py
scipy_maxentropy/maxentutils.py
scipy_maxentropy-1.0.dist-info/LICENSE.md
scipy_maxentropy-1.0.dist-info/METADATA
scipy_maxentropy-1.0.dist-info/WHEEL
scipy_maxentropy-1.0.dist-info/RECORD
