Metadata-Version: 2.1
Name: scipy-maxentropy
Version: 1.0
Summary: Maximum entropy modelling code previously available as scipy.maxentropy
License: BSD
Author: Ed Schofield
Author-email: ed@pythoncharmers.com
Requires-Python: >=3.6,<4.0
Classifier: License :: Other/Proprietary License
Classifier: Programming Language :: Python :: 3
Classifier: Programming Language :: Python :: 3.6
Classifier: Programming Language :: Python :: 3.7
Classifier: Programming Language :: Python :: 3.8
Classifier: Programming Language :: Python :: 3.9
Classifier: Programming Language :: Python :: 3.10
Classifier: Programming Language :: Python :: 3.11
Classifier: Programming Language :: Python :: 3.12
Requires-Dist: scipy (>=1.12.0,<2.0.0)
